odoo/addons/pos_category_multicompany/README.rst
odoo/addons/pos_category_multicompany/__init__.py
odoo/addons/pos_category_multicompany/__manifest__.py
odoo/addons/pos_category_multicompany/demo/res_groups.xml
odoo/addons/pos_category_multicompany/i18n/fr.po
odoo/addons/pos_category_multicompany/i18n/it.po
odoo/addons/pos_category_multicompany/i18n/pos_category_multicompany.pot
odoo/addons/pos_category_multicompany/models/__init__.py
odoo/addons/pos_category_multicompany/models/pos_category.py
odoo/addons/pos_category_multicompany/readme/CONTRIBUTORS.md
odoo/addons/pos_category_multicompany/readme/DESCRIPTION.md
odoo/addons/pos_category_multicompany/security/ir_rule.xml
odoo/addons/pos_category_multicompany/static/description/icon.png
odoo/addons/pos_category_multicompany/static/description/index.html
odoo/addons/pos_category_multicompany/static/description/pos_category_multicompany.jpeg
odoo/addons/pos_category_multicompany/tests/__init__.py
odoo/addons/pos_category_multicompany/tests/test_pos_category_multicompany.py
odoo/addons/pos_category_multicompany/views/view_pos_category.xml
odoo_addon_pos_category_multicompany-18.0.1.0.0.2.dist-info/METADATA
odoo_addon_pos_category_multicompany-18.0.1.0.0.2.dist-info/WHEEL
odoo_addon_pos_category_multicompany-18.0.1.0.0.2.dist-info/top_level.txt
odoo_addon_pos_category_multicompany-18.0.1.0.0.2.dist-info/RECORD
